fixed_income_tools/__init__.py
fixed_income_tools-0.0.1.dist-info/METADATA
fixed_income_tools-0.0.1.dist-info/WHEEL
fixed_income_tools-0.0.1.dist-info/RECORD
