Metadata-Version: 2.4
Name: fixed-income-tools
Version: 0.0.1
Summary: Tools for fixed income analysis
Author-email: Rob Suomi <robert.suomi@gmail.com>
License-Expression: MIT
Requires-Python: >=3.7
